<?xml version="1.0" encoding="UTF-8"?>
<!--
    This file is part of Tryton and Nereid. The COPYRIGHT file at the
    top level of this repository contains the full copyright notices
    and license terms.
-->
<tryton>
  <data>
      <record id="website_cart_info" model="ir.ui.view">
          <field name="model">nereid.website</field>
          <field name="inherit" ref="nereid.website_view_form"/>
          <field name="arch" type="xml">
              <![CDATA[
              <data>
                  <xpath expr="/form/notebook/page[@id='general']/label[@name='timezone']"
                      position="before">
                          <label name="guest_user"/>
                          <field name="guest_user"/>
                  </xpath>
                  <xpath expr="/form/notebook/page[@id='catalog']" 
                      position="inside">
                          <label name="channel"/>
                          <field name="channel"/>
                  </xpath>
              </data>
              ]]>
          </field>
      </record>
  </data>
</tryton>
